fragments
setup.cfg
setup.py
Agora_Fragments.egg-info/PKG-INFO
Agora_Fragments.egg-info/SOURCES.txt
Agora_Fragments.egg-info/dependency_links.txt
Agora_Fragments.egg-info/namespace_packages.txt
Agora_Fragments.egg-info/requires.txt
Agora_Fragments.egg-info/top_level.txt
agora/__init__.py
agora/fragments/__init__.py
agora/fragments/api.py
agora/fragments/metadata.json
agora/fragments/server/__init__.py
agora/fragments/server/config.py