Metadata-Version: 1.1
Name: Agora-Fragments
Version: 0.1.0
Summary: A REST service that provides access to data fragments from a Linked Data Platform powered by Agora
Home-page: https://github.com/smartdeveloperhub/agora-fragments.git
Author: Fernando Serena
Author-email: fernando.serena@centeropenmiddleware.com
License: Apache 2
Download-URL: https://github.com/smartdeveloperhub/agora-fragments/tarball/0.1.0
Keywords: linked-data,ontology,fragments
Platform: UNKNOWN
